ipy_yasi-0.1.2.dist-info/licenses/LICENSE
yasi/__init__.py
yasi/_modidx.py
yasi/core.py
yasi/interfaces.py
ipy_yasi-0.1.2.dist-info/METADATA
ipy_yasi-0.1.2.dist-info/WHEEL
ipy_yasi-0.1.2.dist-info/entry_points.txt
ipy_yasi-0.1.2.dist-info/top_level.txt
ipy_yasi-0.1.2.dist-info/RECORD
