Metadata-Version: 2.4
Name: ipy-yasi
Version: 0.1.2
Summary: DIY alternative to solve it from fast.ai (Yet-Another-SolveIt)
Home-page: https://github.com/Jack-Byte/yasi
Author: Jack-Byte
Author-email: tobi.klings@t-online.de
License: Apache Software License 2.0
Keywords: nbdev jupyter notebook python
Classifier: Development Status :: 4 - Beta
Classifier: Intended Audience :: Developers
Classifier: Natural Language :: English
Classifier: Programming Language :: Python :: 3.10
Classifier: Programming Language :: Python :: 3.11
Classifier: Programming Language :: Python :: 3.12
Classifier: License :: OSI Approved :: Apache Software License
Requires-Python: >=3.10
License-File: LICENSE
Requires-Dist: ipylab>=1.1.0
Requires-Dist: openai>=1.86.0
Requires-Dist: docx2md>=1.0.2
Provides-Extra: dev
Requires-Dist: ipylab>=1.1.0; extra == "dev"
Requires-Dist: openai>=1.86.0; extra == "dev"
Requires-Dist: docx2md>=1.0.2; extra == "dev"
Dynamic: author
Dynamic: author-email
Dynamic: classifier
Dynamic: description
Dynamic: description-content-type
Dynamic: home-page
Dynamic: keywords
Dynamic: license
Dynamic: license-file
Dynamic: provides-extra
Dynamic: requires-dist
Dynamic: requires-python
Dynamic: summary
